sphinx_gemini_builder/__init__.py
sphinx_gemini_builder/ablog_compatibility.py
sphinx_gemini_builder/writer.py
sphinx_gemini_builder/locale/en/LC_MESSAGES/sphinx.po
sphinx_gemini_builder/locale/fr/LC_MESSAGES/sphinx.po
sphinx_gemini_builder-2.0.1.dist-info/entry_points.txt
sphinx_gemini_builder-2.0.1.dist-info/licenses/LICENSE
sphinx_gemini_builder-2.0.1.dist-info/licenses/LICENSE-de
sphinx_gemini_builder-2.0.1.dist-info/licenses/LICENSE-fr
sphinx_gemini_builder-2.0.1.dist-info/licenses/LICENSE-nl
sphinx_gemini_builder-2.0.1.dist-info/WHEEL
sphinx_gemini_builder-2.0.1.dist-info/METADATA
sphinx_gemini_builder-2.0.1.dist-info/RECORD
